flac/__init__.py
flac/functions.py
flacloss-0.0.4.dist-info/METADATA
flacloss-0.0.4.dist-info/WHEEL
flacloss-0.0.4.dist-info/top_level.txt
flacloss-0.0.4.dist-info/RECORD
