Metadata-Version: 2.1
Name: flacloss
Version: 0.0.4
Summary: A loss for learning fair representations when training on data with spurious correlations
Home-page: https://github.com/gsarridis/FLAC
Author: Ioannis Sarridis
Author-email: gsarridis@iti.gr
Classifier: Programming Language :: Python :: 3
Classifier: License :: OSI Approved :: Apache Software License
Classifier: Operating System :: OS Independent
Requires-Python: >=3.6
Requires-Dist: numpy
Requires-Dist: torch
